knvheatpumplib/__init__.py
knvheatpumplib/knvheatpump.py
knvheatpumplib/knvparser.py
knvheatpumplib-0.1.2.dist-info/LICENSE.md
knvheatpumplib-0.1.2.dist-info/METADATA
knvheatpumplib-0.1.2.dist-info/WHEEL
knvheatpumplib-0.1.2.dist-info/top_level.txt
knvheatpumplib-0.1.2.dist-info/RECORD
