Metadata-Version: 2.2
Name: knvheatpumplib
Version: 0.1.2
Summary: KNV heatpump Python library
Author-email: LDprg <lukas_4dr@gmx.at>
License: GPL-3
Project-URL: Homepage, https://github.com/LDprg/KNV_heatpump_lib
License-File: LICENSE.md
